FA_four/full_adder_four.vhdl
library ieee;
use ieee.std_logic_1164.all;

entity full_adder_four is
    port(
        A : in std_logic;
        B : in std_logic;
        Cin : in std_logic;
        Sum : out std_logic;
        Cout : out std_logic
    );
end entity full_adder_four;

architecture rtl of full_adder_four is
    -- Declare signals before use
    signal a1, a2, a3: std_logic;
begin
    -- Half Adder 1
    Sum <= A xor B xor Cin;
    a1 <= A and B;
    a2 <= A and Cin;
    a3 <= B and Cin;
    Cout <= a1 or a2 or a3;
end architecture rtl;

FA_four/full_adder_four_tb.vhdl
library ieee;
use ieee.std_logic_1164.all;

entity full_adder_four_tb is
end entity full_adder_four_tb;

architecture behavior of full_adder_four_tb is
    signal A, B, Cin, Sum, Cout : std_logic := '0';
begin
    uut: entity work.full_adder_four
        port map(A => A, B => B, Cin => Cin, Sum => Sum, Cout => Cout);

    stimulus: process
    begin
        -- Test Cases
        A <= '0'; B <= '0'; Cin <= '0'; wait for 10 ns; -- 0 + 0 + 0 = 0
        A <= '0'; B <= '0'; Cin <= '1'; wait for 10 ns; -- 0 + 0 + 1 = 1
        A <= '0'; B <= '1'; Cin <= '0'; wait for 10 ns; -- 0 + 1 + 0 = 1
        A <= '0'; B <= '1'; Cin <= '1'; wait for 10 ns; -- 0 + 1 + 1 = 0, Cout = 1
        A <= '1'; B <= '0'; Cin <= '0'; wait for 10 ns; -- 1 + 0 + 0 = 1
        A <= '1'; B <= '0'; Cin <= '1'; wait for 10 ns; -- 1 + 0 + 1 = 0, Cout = 1
        A <= '1'; B <= '1'; Cin <= '0'; wait for 10 ns; -- 1 + 1 + 0 = 0
        A <= '1'; B <= '1'; Cin <= '1'; wait for 10 ns; -- 1 + 1 + 1 = 0, Cout = 1

        -- End Simulation
        wait;
    end process stimulus;
end architecture behavior;

FA_four/adder.vcd
$date
  Sat May 11 04:22:23 2024
$end
$version
  GHDL v0
$end
$timescale
  1 fs
$end
$scope module standard $end
$upscope $end
$scope module std_logic_1164 $end
$upscope $end
$scope module full_adder_four_tb $end
$var reg 1 ! a $end
$var reg 1 " b $end
$var reg 1 # cin $end
$var reg 1 $ sum $end
$var reg 1 % cout $end
$scope module uut $end
$var reg 1 & a $end
$var reg 1 ' b $end
$var reg 1 ( cin $end
$var reg 1 ) sum $end
$var reg 1 * cout $end
$var reg 1 + a1 $end
$var reg 1 , a2 $end
$var reg 1 - a3 $end
$upscope $end
$upscope $end
$enddefinitions $end
#0
0!
0"
0#
0$
0%
0&
0'
0(
0)
0*
0+
0,
0-
#10000000
1#
1$
1(
1)
#20000000
1"
0#
1'
0(
#30000000
1#
0$
1%
1(
0)
1*
1-
#40000000
1!
0"
0#
1$
0%
1&
0'
0(
1)
0*
0-
#50000000
1#
0$
1%
1(
0)
1*
1,
#60000000
1"
0#
1'
0(
1+
0,
#70000000
1#
1$
1(
1)
1,
1-
