FA_three/half_adder.vhdl
library ieee;
use ieee.std_logic_1164.all;

entity half_adder is
    Port ( a : in STD_LOGIC;
           b : in STD_LOGIC;
           sum : out STD_LOGIC;
           cout : out STD_LOGIC);
end half_adder;

architecture Behavioral of half_adder is
begin
    -- Sum = A XOR B
    sum <= a xor b;

    -- Carry = A AND B
    cout <= a and b;
end Behavioral;

FA_three/full_adder_three.vhdl
library ieee;
use ieee.std_logic_1164.all;

entity full_adder_three is
    port(
        A : in std_logic;
        B : in std_logic;
        Cin : in std_logic;
        Sum : out std_logic;
        Cout : out std_logic
    );
end entity full_adder_three;

architecture rtl of full_adder_three is

    signal a1, a2, a3: std_logic;

begin
    HA1 : entity work.half_adder port map(a => A, b => B, sum => a1, cout => a2);
    HA2 : entity work.half_adder port map(a => a1, b => Cin, sum => Sum, cout => a3);
    Cout <= a3 or a2;
end architecture rtl ; -- rtl

FA_three/full_adder_three_tb.vhdl
library ieee;
use ieee.std_logic_1164.all;

entity full_adder_three_tb is
end entity full_adder_three_tb;

architecture behavior of full_adder_three_tb is
    signal A, B, Cin, Sum, Cout : std_logic := '0';
begin
    uut: entity work.full_adder_three
        port map(A => A, B => B, Cin => Cin, Sum => Sum, Cout => Cout);

    stimulus: process
    begin
        -- Test Cases
        A <= '0'; B <= '0'; Cin <= '0'; wait for 10 ns; -- 0 + 0 + 0 = 0
        A <= '0'; B <= '0'; Cin <= '1'; wait for 10 ns; -- 0 + 0 + 1 = 1
        A <= '0'; B <= '1'; Cin <= '0'; wait for 10 ns; -- 0 + 1 + 0 = 1
        A <= '0'; B <= '1'; Cin <= '1'; wait for 10 ns; -- 0 + 1 + 1 = 0, Cout = 1
        A <= '1'; B <= '0'; Cin <= '0'; wait for 10 ns; -- 1 + 0 + 0 = 1
        A <= '1'; B <= '0'; Cin <= '1'; wait for 10 ns; -- 1 + 0 + 1 = 0, Cout = 1
        A <= '1'; B <= '1'; Cin <= '0'; wait for 10 ns; -- 1 + 1 + 0 = 0
        A <= '1'; B <= '1'; Cin <= '1'; wait for 10 ns; -- 1 + 1 + 1 = 0, Cout = 1

        -- End Simulation
        wait;
    end process stimulus;
end architecture behavior;

FA_three/adder.vcd
$date
  Sat May 11 04:20:48 2024
$end
$version
  GHDL v0
$end
$timescale
  1 fs
$end
$scope module standard $end
$upscope $end
$scope module std_logic_1164 $end
$upscope $end
$scope module full_adder_three_tb $end
$var reg 1 ! a $end
$var reg 1 " b $end
$var reg 1 # cin $end
$var reg 1 $ sum $end
$var reg 1 % cout $end
$scope module uut $end
$var reg 1 & a $end
$var reg 1 ' b $end
$var reg 1 ( cin $end
$var reg 1 ) sum $end
$var reg 1 * cout $end
$var reg 1 + a1 $end
$var reg 1 , a2 $end
$var reg 1 - a3 $end
$scope module ha1 $end
$var reg 1 . a $end
$var reg 1 / b $end
$var reg 1 0 sum $end
$var reg 1 1 cout $end
$upscope $end
$scope module ha2 $end
$var reg 1 2 a $end
$var reg 1 3 b $end
$var reg 1 4 sum $end
$var reg 1 5 cout $end
$upscope $end
$upscope $end
$upscope $end
$enddefinitions $end
#0
0!
0"
0#
0$
0%
0&
0'
0(
0)
0*
0+
0,
0-
0.
0/
00
01
02
03
04
05
#10000000
1#
1$
1(
1)
13
14
#20000000
1"
0#
1$
1'
0(
1)
1+
1/
10
12
03
14
#30000000
1#
0$
1%
1(
0)
1*
1-
13
04
15
#40000000
1!
0"
0#
1$
0%
1&
0'
0(
1)
0*
0-
1.
0/
03
14
05
#50000000
1#
0$
1%
1(
0)
1*
1-
13
04
15
#60000000
1"
0#
0$
1'
0(
0)
0+
1,
0-
1/
00
11
02
03
04
05
#70000000
1#
1$
1(
1)
13
14
