FA_one/mux2to1.vhdl
library IEEE;
use IEEE.STD_LOGIC_1164.ALL;

entity mux2to1 is
    port (w0: in std_logic; 
          w1: in std_logic; 
          s : in std_logic;
          f : out std_logic);
end entity mux2to1;
  
architecture rtl of mux2to1 is
begin
    -- Concurrent assignment using conditional operator
    f <= w0 when s = '0' else w1;
end architecture rtl;

FA_one/full_adder_one.vhdl
library IEEE;
use IEEE.STD_LOGIC_1164.ALL;

entity full_adder_one is
    port(
        A : in std_logic;
        B : in std_logic;
        Cin : in std_logic;
        Sum : out std_logic;
        Cout : out std_logic
    );
end entity full_adder_one;

architecture rtl of full_adder_one is

    signal a1: std_logic;

begin
    mux_instance : entity work.mux2to1 port map(w0 => A, w1 => Cin, s => a1, f => Cout);
    a1 <= A xor B;
    Sum <= cin xor a1;
end architecture rtl ; -- rtl

FA_one/full_adder_one_tb.vhdl
library ieee;
use ieee.std_logic_1164.all;

entity full_adder_one_tb is
end entity full_adder_one_tb;

architecture behavior of full_adder_one_tb is
    signal A, B, Cin, Sum, Cout : std_logic := '0';
begin
    uut: entity work.full_adder_one
        port map(A => A, B => B, Cin => Cin, Sum => Sum, Cout => Cout);

    stimulus: process
    begin
        -- Test Cases
        A <= '0'; B <= '0'; Cin <= '0'; wait for 10 ns; -- 0 + 0 + 0 = 0
        A <= '0'; B <= '0'; Cin <= '1'; wait for 10 ns; -- 0 + 0 + 1 = 1
        A <= '0'; B <= '1'; Cin <= '0'; wait for 10 ns; -- 0 + 1 + 0 = 1
        A <= '0'; B <= '1'; Cin <= '1'; wait for 10 ns; -- 0 + 1 + 1 = 0, Cout = 1
        A <= '1'; B <= '0'; Cin <= '0'; wait for 10 ns; -- 1 + 0 + 0 = 1
        A <= '1'; B <= '0'; Cin <= '1'; wait for 10 ns; -- 1 + 0 + 1 = 0, Cout = 1
        A <= '1'; B <= '1'; Cin <= '0'; wait for 10 ns; -- 1 + 1 + 0 = 0
        A <= '1'; B <= '1'; Cin <= '1'; wait for 10 ns; -- 1 + 1 + 1 = 0, Cout = 1

        -- End Simulation
        wait;
    end process stimulus;
end architecture behavior;

FA_one/adder.vcd
$date
  Sat May 11 04:15:36 2024
$end
$version
  GHDL v0
$end
$timescale
  1 fs
$end
$scope module standard $end
$upscope $end
$scope module std_logic_1164 $end
$upscope $end
$scope module full_adder_one_tb $end
$var reg 1 ! a $end
$var reg 1 " b $end
$var reg 1 # cin $end
$var reg 1 $ sum $end
$var reg 1 % cout $end
$scope module uut $end
$var reg 1 & a $end
$var reg 1 ' b $end
$var reg 1 ( cin $end
$var reg 1 ) sum $end
$var reg 1 * cout $end
$var reg 1 + a1 $end
$scope module mux_instance $end
$var reg 1 , w0 $end
$var reg 1 - w1 $end
$var reg 1 . s $end
$var reg 1 / f $end
$upscope $end
$upscope $end
$upscope $end
$enddefinitions $end
#0
0!
0"
0#
0$
0%
0&
0'
0(
0)
0*
0+
0,
0-
0.
0/
#10000000
1#
1$
1(
1)
1-
#20000000
1"
0#
1$
1'
0(
1)
1+
0-
1.
#30000000
1#
0$
1%
1(
0)
1*
1-
1/
#40000000
1!
0"
0#
1$
0%
1&
0'
0(
1)
0*
1,
0-
0/
#50000000
1#
0$
1%
1(
0)
1*
1-
1/
#60000000
1"
0#
0$
1%
1'
0(
0)
1*
0+
0-
0.
1/
#70000000
1#
1$
1(
1)
1-
