FA_two/full_adder_two.vhdl
library IEEE;
use IEEE.STD_LOGIC_1164.ALL;

entity full_adder_two is
    port(
        A : in std_logic;
        B : in std_logic;
        Cin : in std_logic;
        Sum : out std_logic;
        Cout : out std_logic
    );
end entity full_adder_two;

architecture rtl of full_adder_two is

    signal a1, a2, a3: std_logic;

begin
    a1 <= A xor B;
    a2 <= Cin and a1;
    a3 <= A and B;
    Sum <= a1 xor Cin;
    Cout <= a2 xor a3;
end architecture rtl ; -- rtl

FA_two/full_adder_two_tb.vhdl
library ieee;
use ieee.std_logic_1164.all;

entity full_adder_two_tb is
end entity full_adder_two_tb;

architecture behavior of full_adder_two_tb is
    signal A, B, Cin, Sum, Cout : std_logic := '0';
begin
    uut: entity work.full_adder_two
        port map(A => A, B => B, Cin => Cin, Sum => Sum, Cout => Cout);

    stimulus: process
    begin
        -- Test Cases
        A <= '0'; B <= '0'; Cin <= '0'; wait for 10 ns; -- 0 + 0 + 0 = 0
        A <= '0'; B <= '0'; Cin <= '1'; wait for 10 ns; -- 0 + 0 + 1 = 1
        A <= '0'; B <= '1'; Cin <= '0'; wait for 10 ns; -- 0 + 1 + 0 = 1
        A <= '0'; B <= '1'; Cin <= '1'; wait for 10 ns; -- 0 + 1 + 1 = 0, Cout = 1
        A <= '1'; B <= '0'; Cin <= '0'; wait for 10 ns; -- 1 + 0 + 0 = 1
        A <= '1'; B <= '0'; Cin <= '1'; wait for 10 ns; -- 1 + 0 + 1 = 0, Cout = 1
        A <= '1'; B <= '1'; Cin <= '0'; wait for 10 ns; -- 1 + 1 + 0 = 0
        A <= '1'; B <= '1'; Cin <= '1'; wait for 10 ns; -- 1 + 1 + 1 = 0, Cout = 1

        -- End Simulation
        wait;
    end process stimulus;
end architecture behavior;

FA_two/adder.vcd
$date
  Sat May 11 04:17:44 2024
$end
$version
  GHDL v0
$end
$timescale
  1 fs
$end
$scope module standard $end
$upscope $end
$scope module std_logic_1164 $end
$upscope $end
$scope module full_adder_two_tb $end
$var reg 1 ! a $end
$var reg 1 " b $end
$var reg 1 # cin $end
$var reg 1 $ sum $end
$var reg 1 % cout $end
$scope module uut $end
$var reg 1 & a $end
$var reg 1 ' b $end
$var reg 1 ( cin $end
$var reg 1 ) sum $end
$var reg 1 * cout $end
$var reg 1 + a1 $end
$var reg 1 , a2 $end
$var reg 1 - a3 $end
$upscope $end
$upscope $end
$enddefinitions $end
#0
0!
0"
0#
0$
0%
0&
0'
0(
0)
0*
0+
0,
0-
#10000000
1#
1$
1(
1)
#20000000
1"
0#
1$
1'
0(
1)
1+
#30000000
1#
0$
1%
1(
0)
1*
1,
#40000000
1!
0"
0#
1$
0%
1&
0'
0(
1)
0*
0,
#50000000
1#
0$
1%
1(
0)
1*
1,
#60000000
1"
0#
0$
1'
0(
0)
0+
0,
1-
#70000000
1#
1$
1(
1)
